documentstack/__init__.py
documentstack/client.py
documentstack/errors.py
documentstack/py.typed
documentstack/types.py
documentstack-1.0.0.dist-info/METADATA
documentstack-1.0.0.dist-info/WHEEL
documentstack-1.0.0.dist-info/RECORD
