Metadata-Version: 2.4
Name: documentstack
Version: 1.0.0
Summary: Official Python SDK for DocumentStack PDF generation API
Project-URL: Homepage, https://documentstack.dev
Project-URL: Documentation, https://documentstack.dev/docs/sdk/python
Project-URL: Repository, https://github.com/documentstack/sdk-python
Project-URL: Changelog, https://github.com/documentstack/sdk-python/blob/main/CHANGELOG.md
Author-email: DocumentStack Team <support@documentstack.dev>
License-Expression: MIT
Keywords: api,document,generation,pdf,sdk,template
Classifier: Development Status :: 5 - Production/Stable
Classifier: Intended Audience :: Developers
Classifier: License :: OSI Approved :: MIT License
Classifier: Operating System :: OS Independent
Classifier: Programming Language :: Python :: 3
Classifier: Programming Language :: Python :: 3.10
Classifier: Programming Language :: Python :: 3.11
Classifier: Programming Language :: Python :: 3.12
Classifier: Typing :: Typed
Requires-Python: >=3.10
Requires-Dist: httpx>=0.24.0
Provides-Extra: dev
Requires-Dist: mypy>=1.0.0; extra == 'dev'
Requires-Dist: pytest-cov>=4.0.0; extra == 'dev'
Requires-Dist: pytest>=7.0.0; extra == 'dev'
Requires-Dist: respx>=0.20.0; extra == 'dev'
Requires-Dist: ruff>=0.1.0; extra == 'dev'
